{
  "block": "1-00262",
  "buildings": [
    {
      "bbl": "1002620025",
      "address": "430 FDR DRIVE WEST LANE",
      "height": 3.6576,
      "color": [
        110,
        120,
        100
      ],
      "buildingClass": "Q1",
      "landUse": "9",
      "yearBuilt": 1910,
      "floors": 2,
      "visible": true,
      "footprint": [
        [
          -1137.6193,
          -1900.0259
        ],
        [
          -1137.5072,
          -1904.5653
        ],
        [
          -1132.6781,
          -1904.4451
        ],
        [
          -1132.7902,
          -1899.9056
        ]
      ],
      "holes": null
    },
    {
      "bbl": "1002620014",
      "address": "397 FDR DRIVE",
      "height": 6.72084,
      "color": [
        110,
        120,
        100
      ],
      "buildingClass": "Q1",
      "landUse": "9",
      "yearBuilt": 0,
      "floors": 1,
      "visible": true,
      "footprint": [
        [
          -1195.4341,
          -1740.4846
        ],
        [
          -1195.9568,
          -1746.7765
        ],
        [
          -1189.4413,
          -1747.3223
        ],
        [
          -1189.5061,
          -1748.1016
        ],
        [
          -1181.6028,
          -1748.7635
        ],
        [
          -1181.5424,
          -1748.0383
        ],
        [
          -1175.1394,
          -1748.5747
        ],
        [
          -1174.6122,
          -1742.2286
        ],
        [
          -1181.0181,
          -1741.6921
        ],
        [
          -1180.982,
          -1741.2592
        ],
        [
          -1188.8827,
          -1740.5974
        ],
        [
          -1188.9186,
          -1741.0304
        ]
      ],
      "holes": null
    }
  ]
}