{
  "block": "1-00465",
  "buildings": [
    {
      "bbl": "1004650011",
      "address": "108 EAST 10 STREET",
      "height": 15.706344,
      "color": [
        130,
        95,
        65
      ],
      "buildingClass": "B9",
      "landUse": "1",
      "yearBuilt": 1867,
      "floors": 4,
      "visible": true,
      "footprint": [
        [
          -453.50192,
          330.5186
        ],
        [
          -446.81732,
          318.25864
        ],
        [
          -440.91855,
          321.4996
        ],
        [
          -447.60315,
          333.75946
        ]
      ],
      "holes": null
    },
    {
      "bbl": "1004650012",
      "address": "110 EAST 10 STREET",
      "height": 14.926056,
      "color": [
        130,
        95,
        65
      ],
      "buildingClass": "B1",
      "landUse": "1",
      "yearBuilt": 1867,
      "floors": 4,
      "visible": true,
      "footprint": [
        [
          -459.6586,
          327.1359
        ],
        [
          -456.36703,
          321.09912
        ],
        [
          -452.97388,
          314.87607
        ],
        [
          -452.7017,
          315.02567
        ],
        [
          -446.81732,
          318.25864
        ],
        [
          -453.50192,
          330.5186
        ],
        [
          -458.8986,
          327.55344
        ]
      ],
      "holes": null
    },
    {
      "bbl": "1004650109",
      "address": "104 EAST 10 STREET",
      "height": 12.566904,
      "color": [
        120,
        85,
        60
      ],
      "buildingClass": "C3",
      "landUse": "2",
      "yearBuilt": 1879,
      "floors": 3,
      "visible": true,
      "footprint": [
        [
          -441.85867,
          336.91562
        ],
        [
          -436.5379,
          327.15698
        ],
        [
          -434.51404,
          328.26895
        ],
        [
          -431.39456,
          329.98285
        ],
        [
          -436.7154,
          339.7415
        ],
        [
          -441.44974,
          337.14032
        ]
      ],
      "holes": null
    },
    {
      "bbl": "1004650016",
      "address": "118 EAST 10 STREET",
      "height": 16.742664,
      "color": [
        120,
        85,
        60
      ],
      "buildingClass": "C0",
      "landUse": "2",
      "yearBuilt": 1861,
      "floors": 5,
      "visible": true,
      "footprint": [
        [
          -478.47192,
          316.79935
        ],
        [
          -478.07974,
          316.08017
        ],
        [
          -473.12128,
          306.98602
        ],
        [
          -468.36807,
          309.59753
        ],
        [
          -472.08624,
          316.41678
        ],
        [
          -473.7188,
          319.41086
        ]
      ],
      "holes": null
    },
    {
      "bbl": "1004650026",
      "address": "27 STUYVESANT STREET",
      "height": 17.062704,
      "color": [
        140,
        100,
        70
      ],
      "buildingClass": "A9",
      "landUse": "1",
      "yearBuilt": 1861,
      "floors": 5,
      "visible": true,
      "footprint": [
        [
          -465.32684,
          299.64325
        ],
        [
          -465.8753,
          291.46744
        ],
        [
          -460.87766,
          291.12958
        ],
        [
          -460.1185,
          302.4468
        ],
        [
          -459.94278,
          305.0657
        ],
        [
          -464.94052,
          305.40347
        ]
      ],
      "holes": null
    },
    {
      "bbl": "1004650024",
      "address": "31 STUYVESANT STREET",
      "height": 16.989553,
      "color": [
        130,
        95,
        65
      ],
      "buildingClass": "B9",
      "landUse": "1",
      "yearBuilt": 1861,
      "floors": 5,
      "visible": true,
      "footprint": [
        [
          -477.03223,
          297.7574
        ],
        [
          -477.4018,
          292.2465
        ],
        [
          -471.49927,
          291.8475
        ],
        [
          -470.95093,
          300.02344
        ],
        [
          -476.85342,
          300.42242
        ]
      ],
      "holes": null
    },
    {
      "bbl": "1004650015",
      "address": "116 EAST 10 STREET",
      "height": 16.6116,
      "color": [
        130,
        95,
        65
      ],
      "buildingClass": "B1",
      "landUse": "1",
      "yearBuilt": 1861,
      "floors": 5,
      "visible": true,
      "footprint": [
        [
          -473.7188,
          319.41086
        ],
        [
          -472.08624,
          316.41678
        ],
        [
          -468.36807,
          309.59753
        ],
        [
          -463.52332,
          312.2595
        ],
        [
          -467.09036,
          318.80157
        ],
        [
          -468.87393,
          322.07272
        ]
      ],
      "holes": null
    },
    {
      "bbl": "1004650014",
      "address": "114 EAST 10 STREET",
      "height": 16.593311,
      "color": [
        130,
        95,
        65
      ],
      "buildingClass": "B9",
      "landUse": "1",
      "yearBuilt": 1861,
      "floors": 5,
      "visible": true,
      "footprint": [
        [
          -468.87393,
          322.07272
        ],
        [
          -467.09036,
          318.80157
        ],
        [
          -463.52332,
          312.2595
        ],
        [
          -458.74814,
          314.88303
        ],
        [
          -460.74307,
          318.5419
        ],
        [
          -464.09875,
          324.69635
        ]
      ],
      "holes": null
    },
    {
      "bbl": "1004650010",
      "address": "106 EAST 10 STREET",
      "height": 14.926056,
      "color": [
        130,
        95,
        65
      ],
      "buildingClass": "B1",
      "landUse": "1",
      "yearBuilt": 1867,
      "floors": 4,
      "visible": true,
      "footprint": [
        [
          -447.60315,
          333.75946
        ],
        [
          -440.91855,
          321.4996
        ],
        [
          -435.17407,
          324.65576
        ],
        [
          -436.5379,
          327.15698
        ],
        [
          -441.85867,
          336.91562
        ]
      ],
      "holes": null
    },
    {
      "bbl": "1004650009",
      "address": "102 EAST 10 STREET",
      "height": 12.079225,
      "color": [
        130,
        95,
        65
      ],
      "buildingClass": "B9",
      "landUse": "1",
      "yearBuilt": 1839,
      "floors": 3,
      "visible": true,
      "footprint": [
        [
          -436.7154,
          339.7415
        ],
        [
          -431.39456,
          329.98285
        ],
        [
          -425.7525,
          333.08273
        ],
        [
          -431.07333,
          342.84128
        ]
      ],
      "holes": null
    },
    {
      "bbl": "1004650029",
      "address": "21 STUYVESANT STREET",
      "height": 16.693895,
      "color": [
        160,
        160,
        165
      ],
      "buildingClass": "O2",
      "landUse": "5",
      "yearBuilt": 1804,
      "floors": 3,
      "visible": true,
      "footprint": [
        [
          -450.28586,
          301.78217
        ],
        [
          -451.0271,
          290.7323
        ],
        [
          -442.33734,
          290.14502
        ],
        [
          -441.25934,
          305.6618
        ],
        [
          -446.7602,
          306.03372
        ],
        [
          -446.54642,
          309.22012
        ],
        [
          -449.77237,
          309.43823
        ]
      ],
      "holes": null
    },
    {
      "bbl": "1004650027",
      "address": "25 STUYVESANT STREET",
      "height": 17.117567,
      "color": [
        140,
        100,
        70
      ],
      "buildingClass": "A9",
      "landUse": "1",
      "yearBuilt": 1861,
      "floors": 5,
      "visible": true,
      "footprint": [
        [
          -460.87766,
          291.12958
        ],
        [
          -456.03708,
          290.80243
        ],
        [
          -455.27792,
          302.11963
        ],
        [
          -460.1185,
          302.4468
        ]
      ],
      "holes": null
    },
    {
      "bbl": "1004650025",
      "address": "29 STUYVESANT STREET",
      "height": 17.004793,
      "color": [
        140,
        100,
        70
      ],
      "buildingClass": "A5",
      "landUse": "1",
      "yearBuilt": 1861,
      "floors": 5,
      "visible": true,
      "footprint": [
        [
          -471.49927,
          291.8475
        ],
        [
          -465.8753,
          291.46744
        ],
        [
          -465.32684,
          299.64325
        ],
        [
          -470.95093,
          300.02344
        ]
      ],
      "holes": null
    },
    {
      "bbl": "1004650028",
      "address": "23 STUYVESANT STREET",
      "height": 16.800575,
      "color": [
        120,
        85,
        60
      ],
      "buildingClass": "C0",
      "landUse": "2",
      "yearBuilt": 1861,
      "floors": 5,
      "visible": true,
      "footprint": [
        [
          -456.03708,
          290.80243
        ],
        [
          -451.04504,
          290.46497
        ],
        [
          -451.0271,
          290.7323
        ],
        [
          -450.28586,
          301.78217
        ],
        [
          -455.27792,
          302.11963
        ]
      ],
      "holes": null
    },
    {
      "bbl": "1004650001",
      "address": "31 3 AVENUE",
      "height": 54.2544,
      "color": [
        160,
        145,
        120
      ],
      "buildingClass": "H8",
      "landUse": "8",
      "yearBuilt": 1986,
      "floors": 16,
      "visible": true,
      "footprint": [
        [
          -431.07333,
          342.84128
        ],
        [
          -425.7525,
          333.08273
        ],
        [
          -420.8573,
          324.10455
        ],
        [
          -422.4614,
          323.2232
        ],
        [
          -423.10925,
          321.39465
        ],
        [
          -416.21857,
          308.75677
        ],
        [
          -421.34763,
          305.93875
        ],
        [
          -419.18082,
          301.96475
        ],
        [
          -420.65747,
          301.15338
        ],
        [
          -421.13495,
          296.05316
        ],
        [
          -425.2622,
          296.3326
        ],
        [
          -425.77423,
          288.71167
        ],
        [
          -419.3721,
          288.27823
        ],
        [
          -413.30594,
          287.8675
        ],
        [
          -413.45267,
          288.1314
        ],
        [
          -415.44656,
          291.7186
        ],
        [
          -403.1349,
          298.3734
        ],
        [
          -403.9373,
          299.86926
        ],
        [
          -393.4235,
          305.64575
        ],
        [
          -395.2602,
          309.01434
        ],
        [
          -394.10605,
          309.64844
        ],
        [
          -395.83936,
          312.82758
        ],
        [
          -394.56,
          313.53046
        ],
        [
          -415.27414,
          351.52167
        ]
      ],
      "holes": null
    },
    {
      "bbl": "1004650013",
      "address": "112 EAST 10 STREET",
      "height": 16.751808,
      "color": [
        120,
        85,
        60
      ],
      "buildingClass": "C4",
      "landUse": "2",
      "yearBuilt": 1861,
      "floors": 5,
      "visible": true,
      "footprint": [
        [
          -464.09875,
          324.69635
        ],
        [
          -460.74307,
          318.5419
        ],
        [
          -458.74814,
          314.88303
        ],
        [
          -456.62665,
          310.99222
        ],
        [
          -455.01736,
          311.87637
        ],
        [
          -454.30878,
          310.577
        ],
        [
          -451.2057,
          312.28198
        ],
        [
          -452.7017,
          315.02567
        ],
        [
          -452.97388,
          314.87607
        ],
        [
          -456.36703,
          321.09912
        ],
        [
          -459.6586,
          327.1359
        ]
      ],
      "holes": null
    },
    {
      "bbl": "1004650032",
      "address": "17 STUYVESANT STREET",
      "height": 17.903952,
      "color": [
        120,
        85,
        60
      ],
      "buildingClass": "C7",
      "landUse": "4",
      "yearBuilt": 1920,
      "floors": 5,
      "visible": true,
      "footprint": [
        [
          -432.1238,
          316.3602
        ],
        [
          -432.55405,
          309.54935
        ],
        [
          -432.77597,
          306.03592
        ],
        [
          -433.07007,
          301.37894
        ],
        [
          -433.31543,
          297.49432
        ],
        [
          -433.37085,
          296.61658
        ],
        [
          -433.83347,
          289.29294
        ],
        [
          -425.77423,
          288.71167
        ],
        [
          -425.2622,
          296.3326
        ],
        [
          -424.25122,
          311.37875
        ],
        [
          -424.6575,
          312.50076
        ],
        [
          -424.12015,
          320.49692
        ],
        [
          -430.4531,
          320.92566
        ],
        [
          -430.83566,
          320.95157
        ],
        [
          -431.04327,
          317.8613
        ],
        [
          -432.0931,
          316.8461
        ]
      ],
      "holes": null
    },
    {
      "bbl": "1004650030",
      "address": "19 STUYVESANT STREET",
      "height": 18.995136,
      "color": [
        120,
        85,
        60
      ],
      "buildingClass": "C1",
      "landUse": "2",
      "yearBuilt": 1900,
      "floors": 5,
      "visible": true,
      "footprint": [
        [
          -441.25934,
          305.6618
        ],
        [
          -442.33734,
          290.14502
        ],
        [
          -442.35855,
          289.83554
        ],
        [
          -437.06943,
          289.49893
        ],
        [
          -433.83347,
          289.29294
        ],
        [
          -433.37085,
          296.61658
        ],
        [
          -433.31543,
          297.49432
        ],
        [
          -433.07007,
          301.37894
        ],
        [
          -432.77597,
          306.03592
        ],
        [
          -432.55405,
          309.54935
        ],
        [
          -432.1238,
          316.3602
        ],
        [
          -440.47937,
          316.89203
        ]
      ],
      "holes": null
    },
    {
      "bbl": "1004650049",
      "address": "155 2 AVENUE",
      "height": 15.752064,
      "color": [
        135,
        115,
        95
      ],
      "buildingClass": "S4",
      "landUse": "4",
      "yearBuilt": 1900,
      "floors": 4,
      "visible": true,
      "footprint": [
        [
          -550.85565,
          259.0202
        ],
        [
          -565.8845,
          250.73581
        ],
        [
          -563.5545,
          246.47646
        ],
        [
          -558.9623,
          249.0079
        ],
        [
          -542.10956,
          258.2976
        ],
        [
          -543.75104,
          261.2983
        ],
        [
          -550.1671,
          257.76154
        ]
      ],
      "holes": null
    },
    {
      "bbl": "1004650021",
      "address": "128 EAST 10 STREET",
      "height": 17.583912,
      "color": [
        120,
        85,
        60
      ],
      "buildingClass": "C2",
      "landUse": "2",
      "yearBuilt": 1861,
      "floors": 5,
      "visible": true,
      "footprint": [
        [
          -497.01736,
          293.57224
        ],
        [
          -496.64764,
          299.08325
        ],
        [
          -495.4367,
          299.0014
        ],
        [
          -498.9933,
          305.52423
        ],
        [
          -504.39594,
          302.4944
        ],
        [
          -504.63837,
          302.35843
        ],
        [
          -505.14783,
          294.7632
        ],
        [
          -505.19067,
          294.12466
        ]
      ],
      "holes": null
    },
    {
      "bbl": "1004650041",
      "address": "",
      "height": 20.766024,
      "color": [
        125,
        115,
        105
      ],
      "buildingClass": "",
      "landUse": "",
      "yearBuilt": 0,
      "floors": 0,
      "visible": true,
      "footprint": [
        [
          -516.9658,
          269.073
        ],
        [
          -513.73425,
          268.83746
        ],
        [
          -513.8984,
          266.5675
        ],
        [
          -515.14636,
          266.65845
        ],
        [
          -515.7203,
          258.72522
        ],
        [
          -504.69766,
          260.8811
        ],
        [
          -504.34103,
          265.81088
        ],
        [
          -505.6154,
          265.90375
        ],
        [
          -505.43436,
          268.40536
        ],
        [
          -501.57047,
          268.12372
        ],
        [
          -501.1336,
          274.16373
        ],
        [
          -501.08817,
          274.79175
        ],
        [
          -516.47107,
          275.91306
        ]
      ],
      "holes": null
    },
    {
      "bbl": "1004650045",
      "address": "46 STUYVESANT STREET",
      "height": 15.614903,
      "color": [
        120,
        85,
        60
      ],
      "buildingClass": "C3",
      "landUse": "2",
      "yearBuilt": 1853,
      "floors": 4,
      "visible": true,
      "footprint": [
        [
          -539.33636,
          276.96518
        ],
        [
          -537.7009,
          273.9753
        ],
        [
          -535.58307,
          270.10376
        ],
        [
          -534.4054,
          267.951
        ],
        [
          -534.9717,
          266.91528
        ],
        [
          -533.9848,
          265.1111
        ],
        [
          -530.05237,
          264.82446
        ],
        [
          -529.1833,
          276.8396
        ],
        [
          -539.68646,
          277.6052
        ]
      ],
      "holes": null
    },
    {
      "bbl": "1004650018",
      "address": "122 EAST 10 STREET",
      "height": 16.965168,
      "color": [
        120,
        85,
        60
      ],
      "buildingClass": "C6",
      "landUse": "2",
      "yearBuilt": 1861,
      "floors": 5,
      "visible": true,
      "footprint": [
        [
          -488.08456,
          311.51785
        ],
        [
          -484.16837,
          304.33548
        ],
        [
          -482.7339,
          301.70456
        ],
        [
          -478.00098,
          304.30502
        ],
        [
          -483.35162,
          314.11826
        ]
      ],
      "holes": null
    },
    {
      "bbl": "1004650023",
      "address": "33 STUYVESANT STREET",
      "height": 17.401031,
      "color": [
        130,
        95,
        65
      ],
      "buildingClass": "B9",
      "landUse": "1",
      "yearBuilt": 1861,
      "floors": 5,
      "visible": true,
      "footprint": [
        [
          -487.2319,
          292.9109
        ],
        [
          -477.4018,
          292.2465
        ],
        [
          -477.03223,
          297.7574
        ],
        [
          -486.86224,
          298.42188
        ]
      ],
      "holes": null
    },
    {
      "bbl": "1004650053",
      "address": "149 2 AVENUE",
      "height": 17.346169,
      "color": [
        135,
        115,
        95
      ],
      "buildingClass": "S5",
      "landUse": "4",
      "yearBuilt": 1910,
      "floors": 3,
      "visible": true,
      "footprint": [
        [
          -536.98065,
          244.88863
        ],
        [
          -542.1823,
          242.0214
        ],
        [
          -551.71326,
          236.7676
        ],
        [
          -556.9243,
          233.89513
        ],
        [
          -554.8284,
          230.06387
        ],
        [
          -555.7885,
          229.53464
        ],
        [
          -556.5726,
          229.10248
        ],
        [
          -553.6854,
          223.82472
        ],
        [
          -552.9353,
          224.23824
        ],
        [
          -548.7017,
          226.57195
        ],
        [
          -532.4789,
          235.5144
        ],
        [
          -527.20013,
          238.42426
        ],
        [
          -522.05334,
          241.2613
        ],
        [
          -522.12524,
          241.39272
        ],
        [
          -524.06995,
          244.9479
        ],
        [
          -526.9036,
          243.3859
        ],
        [
          -529.86975,
          248.8083
        ]
      ],
      "holes": null
    },
    {
      "bbl": "1004650043",
      "address": "42 STUYVESANT STREET",
      "height": 13.447776,
      "color": [
        130,
        95,
        65
      ],
      "buildingClass": "B9",
      "landUse": "1",
      "yearBuilt": 1845,
      "floors": 4,
      "visible": true,
      "footprint": [
        [
          -522.8009,
          262.43927
        ],
        [
          -517.4738,
          262.05087
        ],
        [
          -516.9658,
          269.073
        ],
        [
          -516.47107,
          275.91306
        ],
        [
          -521.7982,
          276.30136
        ]
      ],
      "holes": null
    },
    {
      "bbl": "1004650058",
      "address": "231 EAST 9 STREET",
      "height": 6.729984,
      "color": [
        135,
        120,
        105
      ],
      "buildingClass": "K4",
      "landUse": "4",
      "yearBuilt": 1900,
      "floors": 2,
      "visible": true,
      "footprint": [
        [
          -516.538,
          251.28424
        ],
        [
          -514.20715,
          247.02327
        ],
        [
          -513.5501,
          245.82213
        ],
        [
          -510.22894,
          239.75078
        ],
        [
          -507.84164,
          235.38655
        ],
        [
          -500.96564,
          239.17676
        ],
        [
          -508.70224,
          253.32
        ],
        [
          -509.96344,
          255.62555
        ],
        [
          -517.9086,
          253.78986
        ]
      ],
      "holes": null
    },
    {
      "bbl": "1004650022",
      "address": "35 STUYVESANT STREET",
      "height": 17.672304,
      "color": [
        130,
        95,
        65
      ],
      "buildingClass": "B9",
      "landUse": "1",
      "yearBuilt": 1861,
      "floors": 5,
      "visible": true,
      "footprint": [
        [
          -497.01736,
          293.57224
        ],
        [
          -487.2319,
          292.9109
        ],
        [
          -486.86224,
          298.42188
        ],
        [
          -494.0476,
          298.90747
        ],
        [
          -495.4367,
          299.0014
        ],
        [
          -496.64764,
          299.08325
        ]
      ],
      "holes": null
    },
    {
      "bbl": "1004650057",
      "address": "233 EAST 9 STREET",
      "height": 21.05863,
      "color": [
        120,
        85,
        60
      ],
      "buildingClass": "C1",
      "landUse": "2",
      "yearBuilt": 1900,
      "floors": 6,
      "visible": true,
      "footprint": [
        [
          -507.84164,
          235.38655
        ],
        [
          -510.22894,
          239.75078
        ],
        [
          -511.47592,
          239.72433
        ],
        [
          -514.1487,
          244.61058
        ],
        [
          -514.73615,
          245.68442
        ],
        [
          -514.20715,
          247.02327
        ],
        [
          -516.538,
          251.28424
        ],
        [
          -519.3442,
          249.73737
        ],
        [
          -519.6696,
          250.33228
        ],
        [
          -521.40845,
          250.00964
        ],
        [
          -523.7236,
          248.7335
        ],
        [
          -522.0765,
          245.72238
        ],
        [
          -521.3628,
          246.11574
        ],
        [
          -519.20306,
          242.16751
        ],
        [
          -517.6198,
          239.27318
        ],
        [
          -518.89453,
          238.57048
        ],
        [
          -519.2085,
          239.14433
        ],
        [
          -523.07666,
          237.01208
        ],
        [
          -521.8361,
          234.74423
        ],
        [
          -522.2406,
          233.55768
        ],
        [
          -519.6734,
          228.86458
        ]
      ],
      "holes": null
    },
    {
      "bbl": "1004650059",
      "address": "229 EAST 9 STREET",
      "height": 8.226552,
      "color": [
        135,
        120,
        105
      ],
      "buildingClass": "K4",
      "landUse": "4",
      "yearBuilt": 1900,
      "floors": 2,
      "visible": true,
      "footprint": [
        [
          -509.96344,
          255.62555
        ],
        [
          -508.70224,
          253.32
        ],
        [
          -500.96564,
          239.17676
        ],
        [
          -494.38846,
          242.80222
        ],
        [
          -494.6291,
          243.24205
        ],
        [
          -497.35397,
          248.22343
        ],
        [
          -502.5379,
          257.70026
        ]
      ],
      "holes": null
    },
    {
      "bbl": "1004650050",
      "address": "151 2 AVENUE",
      "height": 19.869913,
      "color": [
        120,
        85,
        60
      ],
      "buildingClass": "C7",
      "landUse": "4",
      "yearBuilt": 1900,
      "floors": 6,
      "visible": true,
      "footprint": [
        [
          -558.9623,
          249.0079
        ],
        [
          -563.5545,
          246.47646
        ],
        [
          -564.7422,
          245.82178
        ],
        [
          -557.9182,
          233.34724
        ],
        [
          -556.9243,
          233.89513
        ],
        [
          -551.71326,
          236.7676
        ],
        [
          -553.6614,
          240.3289
        ],
        [
          -545.12695,
          245.03331
        ],
        [
          -543.73816,
          244.86551
        ],
        [
          -542.1823,
          242.0214
        ],
        [
          -536.98065,
          244.88863
        ],
        [
          -538.1837,
          247.08792
        ],
        [
          -538.14984,
          248.42148
        ],
        [
          -536.677,
          249.23338
        ],
        [
          -536.06726,
          248.11864
        ],
        [
          -530.1205,
          251.3967
        ],
        [
          -533.68896,
          257.9203
        ],
        [
          -540.36847,
          254.23836
        ],
        [
          -541.56213,
          256.4205
        ],
        [
          -556.1148,
          248.39864
        ],
        [
          -555.3542,
          247.00815
        ],
        [
          -556.5613,
          246.34274
        ],
        [
          -557.8507,
          246.9758
        ]
      ],
      "holes": null
    },
    {
      "bbl": "1004650046",
      "address": "48 STUYVESANT STREET",
      "height": 23.259287,
      "color": [
        120,
        85,
        60
      ],
      "buildingClass": "C1",
      "landUse": "2",
      "yearBuilt": 1900,
      "floors": 7,
      "visible": true,
      "footprint": [
        [
          -533.9848,
          265.1111
        ],
        [
          -534.9717,
          266.91528
        ],
        [
          -534.4054,
          267.951
        ],
        [
          -535.58307,
          270.10376
        ],
        [
          -536.90375,
          269.87
        ],
        [
          -538.1359,
          272.12244
        ],
        [
          -537.7009,
          273.9753
        ],
        [
          -539.33636,
          276.96518
        ],
        [
          -546.26904,
          277.41077
        ],
        [
          -547.83966,
          276.54492
        ],
        [
          -545.0709,
          271.48358
        ],
        [
          -543.5783,
          271.25253
        ],
        [
          -542.3539,
          269.01434
        ],
        [
          -543.0291,
          267.75095
        ],
        [
          -541.8806,
          265.6515
        ],
        [
          -540.4176,
          265.47467
        ],
        [
          -538.1645,
          261.35583
        ],
        [
          -537.047,
          261.9718
        ],
        [
          -536.40814,
          260.80374
        ],
        [
          -532.7359,
          262.828
        ]
      ],
      "holes": null
    },
    {
      "bbl": "1004650055",
      "address": "145 2 AVENUE",
      "height": 23.19223,
      "color": [
        150,
        140,
        130
      ],
      "buildingClass": "D9",
      "landUse": "3",
      "yearBuilt": 1920,
      "floors": 7,
      "visible": true,
      "footprint": [
        [
          -532.4789,
          235.5144
        ],
        [
          -531.68164,
          234.05705
        ],
        [
          -547.90454,
          225.11461
        ],
        [
          -548.7017,
          226.57195
        ],
        [
          -552.9353,
          224.23824
        ],
        [
          -547.41437,
          214.1454
        ],
        [
          -546.75543,
          214.50868
        ],
        [
          -538.9166,
          218.82967
        ],
        [
          -521.6791,
          228.3314
        ],
        [
          -527.20013,
          238.42426
        ]
      ],
      "holes": null
    },
    {
      "bbl": "1004650048",
      "address": "157 2 AVENUE",
      "height": 16.8402,
      "color": [
        135,
        115,
        95
      ],
      "buildingClass": "S9",
      "landUse": "4",
      "yearBuilt": 1900,
      "floors": 5,
      "visible": true,
      "footprint": [
        [
          -558.0944,
          263.1295
        ],
        [
          -560.4141,
          261.85083
        ],
        [
          -565.96747,
          258.78964
        ],
        [
          -569.2887,
          256.9589
        ],
        [
          -565.8845,
          250.73581
        ],
        [
          -550.85565,
          259.0202
        ],
        [
          -544.5889,
          262.47464
        ],
        [
          -546.8517,
          266.6111
        ],
        [
          -553.1184,
          263.15668
        ],
        [
          -554.2598,
          265.2432
        ]
      ],
      "holes": null
    },
    {
      "bbl": "1004650037",
      "address": "28 STUYVESANT STREET",
      "height": 27.1272,
      "color": [
        145,
        135,
        125
      ],
      "buildingClass": "W4",
      "landUse": "8",
      "yearBuilt": 1920,
      "floors": 6,
      "visible": true,
      "footprint": [
        [
          -497.35397,
          248.22343
        ],
        [
          -494.6291,
          243.24205
        ],
        [
          -481.39703,
          250.53586
        ],
        [
          -457.20322,
          263.77682
        ],
        [
          -456.69107,
          270.953
        ],
        [
          -481.29657,
          272.7225
        ],
        [
          -486.1383,
          273.0707
        ],
        [
          -501.1336,
          274.16373
        ],
        [
          -501.57047,
          268.12372
        ],
        [
          -502.10452,
          260.74124
        ],
        [
          -491.7898,
          259.9894
        ],
        [
          -492.31293,
          258.92484
        ],
        [
          -496.931,
          256.3793
        ],
        [
          -498.1372,
          258.58432
        ],
        [
          -502.31876,
          258.858
        ],
        [
          -502.47318,
          257.58197
        ]
      ],
      "holes": null
    },
    {
      "bbl": "1004650019",
      "address": "124 EAST 10 STREET",
      "height": 17.196815,
      "color": [
        140,
        100,
        70
      ],
      "buildingClass": "A9",
      "landUse": "1",
      "yearBuilt": 1861,
      "floors": 5,
      "visible": true,
      "footprint": [
        [
          -493.25793,
          308.6755
        ],
        [
          -489.34164,
          301.49304
        ],
        [
          -484.16837,
          304.33548
        ],
        [
          -488.08456,
          311.51785
        ]
      ],
      "holes": null
    },
    {
      "bbl": "1004650017",
      "address": "120 EAST 10 STREET",
      "height": 16.85544,
      "color": [
        120,
        85,
        60
      ],
      "buildingClass": "C2",
      "landUse": "2",
      "yearBuilt": 1861,
      "floors": 5,
      "visible": true,
      "footprint": [
        [
          -483.35162,
          314.11826
        ],
        [
          -478.00098,
          304.30502
        ],
        [
          -473.12128,
          306.98602
        ],
        [
          -478.07974,
          316.08017
        ],
        [
          -478.47192,
          316.79935
        ],
        [
          -479.8463,
          316.04422
        ]
      ],
      "holes": null
    },
    {
      "bbl": "1004650020",
      "address": "126 EAST 10 STREET",
      "height": 17.196815,
      "color": [
        120,
        85,
        60
      ],
      "buildingClass": "C2",
      "landUse": "2",
      "yearBuilt": 1861,
      "floors": 5,
      "visible": true,
      "footprint": [
        [
          -498.9933,
          305.52423
        ],
        [
          -495.4367,
          299.0014
        ],
        [
          -494.0476,
          298.90747
        ],
        [
          -489.34164,
          301.49304
        ],
        [
          -493.25793,
          308.6755
        ]
      ],
      "holes": null
    },
    {
      "bbl": "1004650044",
      "address": "44 STUYVESANT STREET",
      "height": 15.218664,
      "color": [
        140,
        100,
        70
      ],
      "buildingClass": "A9",
      "landUse": "1",
      "yearBuilt": 1795,
      "floors": 3,
      "visible": true,
      "footprint": [
        [
          -530.05237,
          264.82446
        ],
        [
          -530.2621,
          261.92557
        ],
        [
          -522.87695,
          261.3873
        ],
        [
          -522.8009,
          262.43927
        ],
        [
          -521.7982,
          276.30136
        ],
        [
          -529.1833,
          276.8396
        ]
      ],
      "holes": null
    },
    {
      "bbl": "1004650047",
      "address": "159 2 AVENUE",
      "height": 23.335487,
      "color": [
        150,
        140,
        130
      ],
      "buildingClass": "D7",
      "landUse": "4",
      "yearBuilt": 1940,
      "floors": 7,
      "visible": true,
      "footprint": [
        [
          -569.2887,
          256.9589
        ],
        [
          -565.96747,
          258.78964
        ],
        [
          -565.75806,
          259.9908
        ],
        [
          -561.51624,
          262.32904
        ],
        [
          -560.4141,
          261.85083
        ],
        [
          -558.0944,
          263.1295
        ],
        [
          -558.5459,
          263.95483
        ],
        [
          -554.8372,
          265.99927
        ],
        [
          -553.846,
          265.4713
        ],
        [
          -549.35223,
          267.94852
        ],
        [
          -549.7651,
          268.70322
        ],
        [
          -546.48663,
          270.51038
        ],
        [
          -549.34326,
          275.73233
        ],
        [
          -550.60144,
          275.93582
        ],
        [
          -574.3723,
          262.83246
        ],
        [
          -574.53345,
          261.82278
        ],
        [
          -571.2741,
          255.86443
        ]
      ],
      "holes": null
    }
  ]
}